LICENSE.txt
MANIFEST.in
README.md
admin.jpg
djesewa.png
pyproject.toml
setup.cfg
setup.py
app/__init__.py
app/admin.py
app/apps.py
app/models.py
app/serializers.py
app/tests.py
app/urls.py
app/views.py
app/migrations/0001_initial.py
app/migrations/0002_auto_20220414_1300.py
app/migrations/0003_auto_20220430_1815.py
app/migrations/0004_auto_20220430_1940.py
app/migrations/0005_auto_20220501_1546.py
app/migrations/__init__.py
app/static/css/style.css
app/static/js/passwordChecker.js
app/templates/esewarequest.html
app/templates/home.html
app/templates/index.html
app/templates/khaltirequest.html
app/templates/login.html
app/templates/payment.html
app/templates/sub.html
app/templates/subscribe.html
app/templates/subscribed.html
app/templates/subscription.html
paradox_pay.egg-info/PKG-INFO
paradox_pay.egg-info/SOURCES.txt
paradox_pay.egg-info/dependency_links.txt
paradox_pay.egg-info/top_level.txt
shop/__init__.py
shop/admin.py
shop/apps.py
shop/forms.py
shop/models.py
shop/tests.py
shop/urls.py
shop/views.py
shop/migrations/0001_initial.py
shop/migrations/0002_delete_esewa.py
shop/migrations/0003_esewa.py
shop/migrations/0004_khalti.py
shop/migrations/__init__.py
shop/templates/shop/addtocart.html
shop/templates/shop/base.html
shop/templates/shop/checkout.html
shop/templates/shop/esewarequest.html
shop/templates/shop/home.html
shop/templates/shop/khaltirequest.html
shop/templates/shop/mycart.html